{
  "meta": {
    "build": {
      "build-date": "2021-11-24",
      "ci-build-number": "1.0.1113",
      "ci-project": "test/cityofsanmateo/law-xml",
      "codified-date": "2021-12-15",
      "platform": {
        "reproducible": "false",
        "version": "2.5.0"
      },
      "repositories": [
        {
          "commit": "618470c01f5bf2f9497b0013bae6424f2b2a9fae",
          "name": "cityofsanmateo/law-xml"
        },
        {
          "commit": "ae1ced33bc8f98fbe818bfefefeeec7cffb84de1",
          "name": "cityofsanmateo/law-xml-codified-preview"
        }
      ]
    },
    "canonical-urls": {
      "html": "https://sanmateo.ca.us.open.law",
      "html-bulk": "https://github.com/oll-test-repos/cityofsanmateo-law-html",
      "static-assets": "https://github.com/oll-test-repos/openlawlibrary-law-static-assets",
      "xml-bulk": "https://github.com/oll-test-repos/cityofsanmateo-law-xml"
    },
    "contact": {
      "email": "help@openlawlib.org"
    },
    "description": "Browse the laws and code of San Mateo",
    "history-start": "2018-03-05",
    "law-url": "https://github.com/oll-test-repos/cityofsanmateo-law"
  }
}