{"t": "Ord. No. 2023-3. Zoning Code Amendments for City Projects, Modifications to Planning Applications, and Height Limitations and Exemptions", "p": "/us/ca/cities/san-mateo/ordinances/2023/3", "et": "document", "sc": "Ord. No. 2023-3", "rd": "City of San Mateo, Cal., Ord. No. 2023-3", "sp": "library|us/ca/cities/san-mateo/ordinances|2023|City of San Mateo, Cal., Ord. No. 2023-3", "sd": true, "c": [{"t": "Section 1.", "p": "/us/ca/cities/san-mateo/ordinances/2023/3#1", "et": "section", "sc": "Section 1", "cn": "\u00a71", "sp": "library|us/ca/cities/san-mateo/ordinances|2023|City of San Mateo, Cal., Ord. No. 2023-3|1", "x": "Legislative Findings."}, {"t": "Section 2.", "p": "/us/ca/cities/san-mateo/ordinances/2023/3#2", "et": "section", "sc": "Section 2", "cn": "\u00a72", "sp": "library|us/ca/cities/san-mateo/ordinances|2023|City of San Mateo, Cal., Ord. No. 2023-3|2", "x": "Section 27.02.060 of the San Mateo Municipal Code is amended as follows:"}, {"t": "Section 3.", "p": "/us/ca/cities/san-mateo/ordinances/2023/3#3", "et": "section", "sc": "Section 3", "cn": "\u00a73", "sp": "library|us/ca/cities/san-mateo/ordinances|2023|City of San Mateo, Cal., Ord. No. 2023-3|3", "x": "Section 27.02.140 of the San Mateo Municipal Code is amended as follows:"}, {"t": "Section 4.", "p": "/us/ca/cities/san-mateo/ordinances/2023/3#4", "et": "section", "sc": "Section 4", "cn": "\u00a74", "sp": "library|us/ca/cities/san-mateo/ordinances|2023|City of San Mateo, Cal., Ord. No. 2023-3|4", "x": "Section 27.06.020 of the San Mateo Municipal Code is amended as follows:"}, {"t": "Section 5.", "p": "/us/ca/cities/san-mateo/ordinances/2023/3#5", "et": "section", "sc": "Section 5", "cn": "\u00a75", "sp": "library|us/ca/cities/san-mateo/ordinances|2023|City of San Mateo, Cal., Ord. No. 2023-3|5", "x": "Section 27.06.050 of the San Mateo Municipal Code is amended as follows:"}, {"t": "Section 6.", "p": "/us/ca/cities/san-mateo/ordinances/2023/3#6", "et": "section", "sc": "Section 6", "cn": "\u00a76", "sp": "library|us/ca/cities/san-mateo/ordinances|2023|City of San Mateo, Cal., Ord. No. 2023-3|6", "x": "Section 27.08.080 of the San Mateo Municipal Code is amended as follows:"}, {"t": "Section 7. Environmental Determination.", "p": "/us/ca/cities/san-mateo/ordinances/2023/3#7", "et": "section", "sc": "Section 7", "cn": "\u00a77", "sp": "library|us/ca/cities/san-mateo/ordinances|2023|City of San Mateo, Cal., Ord. No. 2023-3|7"}, {"t": "Section 8. Severability.", "p": "/us/ca/cities/san-mateo/ordinances/2023/3#8", "et": "section", "sc": "Section 8", "cn": "\u00a78", "sp": "library|us/ca/cities/san-mateo/ordinances|2023|City of San Mateo, Cal., Ord. No. 2023-3|8"}, {"t": "Section 9. Publication.", "p": "/us/ca/cities/san-mateo/ordinances/2023/3#9", "et": "section", "sc": "Section 9", "cn": "\u00a79", "sp": "library|us/ca/cities/san-mateo/ordinances|2023|City of San Mateo, Cal., Ord. No. 2023-3|9"}, {"t": "Section 10. Legislative History and Effective Date.", "p": "/us/ca/cities/san-mateo/ordinances/2023/3#10", "et": "section", "sc": "Section 10", "cn": "\u00a710", "sp": "library|us/ca/cities/san-mateo/ordinances|2023|City of San Mateo, Cal., Ord. No. 2023-3|10"}]}