{"t": "Ord. No. 2024-10. Measure T \u2013 General Plan Land Use Element", "p": "/us/ca/cities/san-mateo/ordinances/2024/10", "et": "document", "sc": "Ord. No. 2024-10", "rd": "City of San Mateo, Cal., Ord. No. 2024-10", "ei": "us/ca/cities/san-mateo/docs/ordinance", "sp": "library|us/ca/cities/san-mateo/ordinances|2024|City of San Mateo, Cal., Ord. No. 2024-10", "sd": true, "xp": "/us/ca/cities/san-mateo/ordinances/2024/10.xml", "c": [{"t": "Section 1.", "p": "/us/ca/cities/san-mateo/ordinances/2024/10#1", "et": "section", "sc": "Section 1", "rp": "\u00a71", "sp": "library|us/ca/cities/san-mateo/ordinances|2024|City of San Mateo, Cal., Ord. No. 2024-10|1", "x": "The Land Use Element of the General Plan, attached hereto as Attachment 1 a"}, {"t": "Section 2.", "p": "/us/ca/cities/san-mateo/ordinances/2024/10#2", "et": "section", "sc": "Section 2", "rp": "\u00a72", "sp": "library|us/ca/cities/san-mateo/ordinances|2024|City of San Mateo, Cal., Ord. No. 2024-10|2", "x": "New land use designations may be created, but no new land use designations "}, {"t": "Section 3.", "p": "/us/ca/cities/san-mateo/ordinances/2024/10#3", "et": "section", "sc": "Section 3", "rp": "\u00a73", "sp": "library|us/ca/cities/san-mateo/ordinances|2024|City of San Mateo, Cal., Ord. No. 2024-10|3", "x": "Appendix A to the Land Use Element of the General Plan, attached hereto as "}, {"t": "Section 4.", "p": "/us/ca/cities/san-mateo/ordinances/2024/10#4", "et": "section", "sc": "Section 4", "rp": "\u00a74", "sp": "library|us/ca/cities/san-mateo/ordinances|2024|City of San Mateo, Cal., Ord. No. 2024-10|4", "x": "Measure Y, attached hereto as Attachment 3 and incorporated by reference, i"}, {"t": "Section 5.", "p": "/us/ca/cities/san-mateo/ordinances/2024/10#5", "et": "section", "sc": "Section 5", "rp": "\u00a75", "sp": "library|us/ca/cities/san-mateo/ordinances|2024|City of San Mateo, Cal., Ord. No. 2024-10|5", "x": "Specific Properties."}, {"t": "Section 6.", "p": "/us/ca/cities/san-mateo/ordinances/2024/10#6", "et": "section", "sc": "Section 6", "rp": "\u00a76", "sp": "library|us/ca/cities/san-mateo/ordinances|2024|City of San Mateo, Cal., Ord. No. 2024-10|6", "x": "Conforming Changes"}, {"t": "Section 7.", "p": "/us/ca/cities/san-mateo/ordinances/2024/10#7", "et": "section", "sc": "Section 7", "rp": "\u00a77", "sp": "library|us/ca/cities/san-mateo/ordinances|2024|City of San Mateo, Cal., Ord. No. 2024-10|7", "x": "Unconstitutional Takings"}, {"t": "Section 8.", "p": "/us/ca/cities/san-mateo/ordinances/2024/10#8", "et": "section", "sc": "Section 8", "rp": "\u00a78", "sp": "library|us/ca/cities/san-mateo/ordinances|2024|City of San Mateo, Cal., Ord. No. 2024-10|8", "x": "Severability"}, {"t": "Section 9.", "p": "/us/ca/cities/san-mateo/ordinances/2024/10#9", "et": "section", "sc": "Section 9", "rp": "\u00a79", "sp": "library|us/ca/cities/san-mateo/ordinances|2024|City of San Mateo, Cal., Ord. No. 2024-10|9", "x": "Effective Date and Duration"}, {"t": "Section 10.", "p": "/us/ca/cities/san-mateo/ordinances/2024/10#10", "et": "section", "sc": "Section 10", "rp": "\u00a710", "sp": "library|us/ca/cities/san-mateo/ordinances|2024|City of San Mateo, Cal., Ord. No. 2024-10|10", "x": "Conflicting Ballot Measures"}, {"t": "Section 11.", "p": "/us/ca/cities/san-mateo/ordinances/2024/10#11", "et": "section", "sc": "Section 11", "rp": "\u00a711", "sp": "library|us/ca/cities/san-mateo/ordinances|2024|City of San Mateo, Cal., Ord. No. 2024-10|11", "x": "Publication"}, {"t": "Section 12.", "p": "/us/ca/cities/san-mateo/ordinances/2024/10#12", "et": "section", "sc": "Section 12", "rp": "\u00a712", "sp": "library|us/ca/cities/san-mateo/ordinances|2024|City of San Mateo, Cal., Ord. No. 2024-10|12", "x": "Legislative History And Effective Date"}, {"t": "Ordinance Attachment 1 General Plan Land Use Element", "p": "/us/ca/cities/san-mateo/ordinances/2024/10#attachments/att-1", "et": "attachment", "sc": "Ordinance Attachment 1", "rp": "attachments|att-1", "sp": "library|us/ca/cities/san-mateo/ordinances|2024|City of San Mateo, Cal., Ord. No. 2024-10|att-1"}, {"t": "Ordinance Attachment 1A General Plan Land Use Map - Individual Parcels", "p": "/us/ca/cities/san-mateo/ordinances/2024/10#attachments/att-1a", "et": "attachment", "sc": "Ordinance Attachment 1A", "rp": "attachments|att-1A", "sp": "library|us/ca/cities/san-mateo/ordinances|2024|City of San Mateo, Cal., Ord. No. 2024-10|att-1A"}, {"t": "Ordinance Attachment 2 General Plan Land Use Element Appendix A", "p": "/us/ca/cities/san-mateo/ordinances/2024/10#attachments/att-2", "et": "attachment", "sc": "Ordinance Attachment 2", "rp": "attachments|att-2", "sp": "library|us/ca/cities/san-mateo/ordinances|2024|City of San Mateo, Cal., Ord. No. 2024-10|att-2"}, {"t": "Ordinance Attachment 3 Measure Y \u2013 strikethrough text", "p": "/us/ca/cities/san-mateo/ordinances/2024/10#attachments/att-3", "et": "attachment", "sc": "Ordinance Attachment 3", "rp": "attachments|att-3", "sp": "library|us/ca/cities/san-mateo/ordinances|2024|City of San Mateo, Cal., Ord. No. 2024-10|att-3"}]}